torch_ngram/torch_ngram.py
torch_ngram-0.0.1.dist-info/METADATA
torch_ngram-0.0.1.dist-info/WHEEL
torch_ngram-0.0.1.dist-info/top_level.txt
torch_ngram-0.0.1.dist-info/RECORD
