Metadata-Version: 2.1
Name: torch-ngram
Version: 0.0.1
Summary: a pytorch tool to calculate n-gram overlap between two tensors
Home-page: https://scholar.google.com/citations?user=fY69CxIAAAAJ&hl=zh-CN
Author: Chenxin
Author-email: cxan20@fudan.edu.cn
